edge_detector.v
`ifndef EDGE_DETECTOR_V
`define EDGE_DETECTOR_V

module edge_detector (
    input wire sys_clk,
    input wire rst_n,
    input wire signal_in,
    output wire neg_edge
);
    reg delay_reg;

    always @(posedge sys_clk or negedge rst_n) begin
        if (!rst_n) begin
            delay_reg <= 1'b1;
        end else begin
            delay_reg <= signal_in;
        end
    end
    
    assign neg_edge = delay_reg & ~signal_in;
endmodule

`endif

baud_gen.v
`ifndef BAUD_GEN_V
`define BAUD_GEN_V

module baud_gen (
    input wire sys_clk,
    input wire rst_n,
    output reg baud_clk
);
    reg [3:0] counter;

    always @(posedge sys_clk or negedge rst_n) begin
        if (!rst_n) begin
            counter  <= 4'd0;
            baud_clk <= 1'b0;
        end else begin
            if (counter == 4'd7) begin // Toggles every 8 cycles for a divide-by-16 period
                counter  <= 4'd0;
                baud_clk <= ~baud_clk;
            end else begin
                counter <= counter + 1'b1;
            end
        end
    end
endmodule

`endif

uart_receiver.v
`include "baud_gen.v"
`include "edge_detector.v"

module uart_receiver (
    input wire sys_clk,
    input wire rst_n,
    input wire serial_data_in,
    output reg [7:0] parallel_data_out,
    output reg data_valid,
    output reg busy
);
    wire baud_clk;
    wire start_detect_pulse;
    reg start_flag;

    // Baud rate generator block
    baud_gen b_gen (
        .sys_clk(sys_clk),
        .rst_n(rst_n),
        .baud_clk(baud_clk)
    );

    // Edge detector runs on the high-speed sys_clk to catch the exact edge transition
    edge_detector ed_det (
        .sys_clk(sys_clk),
        .rst_n(rst_n),
        .signal_in(serial_data_in),
        .neg_edge(start_detect_pulse)
    );

    // Catch the brief edge pulse and hold it high until the FSM leaves IDLE
    always @(negedge sys_clk or negedge rst_n) begin
        if (!rst_n) begin
            start_flag <= 1'b0;
        end else begin
            if (start_detect_pulse)
                start_flag <= 1'b1;
            else if (state != IDLE) // Clear the flag once the FSM acknowledges it
                start_flag <= 1'b0;
        end
    end

    // FSM States
    localparam IDLE  = 2'b00;
    localparam SHIFT = 2'b01;
    localparam LOAD  = 2'b10;
    localparam WAIT  = 2'b11;

    reg [1:0] state, next_state;
    reg [3:0] bit_count;
    reg [10:0] rx_shift_reg;

    // FSM State Register
    always @(posedge baud_clk or negedge rst_n) begin
        if (!rst_n) state <= IDLE;
        else        state <= next_state;
    end

    // Next State Logic
    always @(*) begin
        case (state)
            IDLE:  next_state = start_flag ? SHIFT : IDLE;
            SHIFT: next_state = (bit_count >= 4'd10) ? LOAD : SHIFT;
            LOAD:  next_state = WAIT;
            WAIT:  next_state = IDLE;
            default: next_state = IDLE;
        endcase
    end

    // Datapath Output Logic
    always @(negedge baud_clk or negedge rst_n) begin
        if (!rst_n) begin
            parallel_data_out <= 8'b0;
            data_valid        <= 1'b0;
            busy              <= 1'b0;
            bit_count         <= 4'd0;
            rx_shift_reg      <= 11'b0;
        end else begin
            case (state)
                IDLE: begin
                    data_valid <= 1'b0;
                    busy       <= 1'b0;
                    bit_count  <= 4'd0;
                end
                SHIFT: begin
                    busy         <= 1'b1;
                    rx_shift_reg <= {serial_data_in, rx_shift_reg[10:1]};
                    bit_count    <= bit_count + 1'b1;
                end
                LOAD: begin
                    busy <= 1'b1;
                    // Check if the calculated odd parity of data bits matches the received parity bit
                    if (~(^rx_shift_reg[8:1]) == rx_shift_reg[9]) begin
                        parallel_data_out <= rx_shift_reg[8:1]; 
                        data_valid        <= 1'b1;
                    end
                end
                WAIT: begin
                    busy       <= 1'b0;
                    data_valid <= 1'b0;
                end
            endcase
        end
    end
endmodule

parity_gen.v
`ifndef PARITY_GEN_V
`define PARITY_GEN_V

module parity_gen (
    input wire [7:0] tx_data_in,
    input wire even_odd, 
    output reg parity_bit
);
    always @(*) begin
        if (even_odd) begin
            parity_bit = ~(^tx_data_in); // Odd parity bit calculation
        end else begin
            parity_bit = ^tx_data_in;   // Even parity bit calculation
        end
    end
endmodule

`endif

uart_transmitter.v
`include "baud_gen.v"
`include "parity_gen.v"

module uart_transmitter (
    input wire sys_clk,
    input wire rst_n,
    input wire tx_enable,
    input wire [7:0] tx_data_in,
    input wire even_odd,
    output reg serial_out,
    output reg busy
);
    wire baud_clk;
    wire parity_bit;
    
    baud_gen b_gen (
        .sys_clk(sys_clk),
        .rst_n(rst_n),
        .baud_clk(baud_clk)
    );

    parity_gen p_gen (
        .tx_data_in(tx_data_in),
        .even_odd(even_odd),
        .parity_bit(parity_bit)
    );

    localparam IDLE  = 2'b00;
    localparam LOAD  = 2'b01;
    localparam SHIFT = 2'b10;
    localparam WAIT  = 2'b11;

    reg [1:0] state, next_state;
    reg [10:0] tx_shift_reg; 
    reg [3:0] bit_count;

    always @(posedge baud_clk or negedge rst_n) begin
        if (!rst_n) begin
            state <= IDLE;
        end else begin
            state <= next_state;
        end
    end

    always @(*) begin
        case (state)
            IDLE:  next_state = tx_enable ? LOAD : IDLE;
            LOAD:  next_state = SHIFT;
            SHIFT: next_state = (bit_count >= 4'd11) ? WAIT : SHIFT;
            WAIT:  next_state = IDLE;
            default: next_state = IDLE;
        endcase
    end

    always @(posedge baud_clk or negedge rst_n) begin
        if (!rst_n) begin
            serial_out   <= 1'b1;
            busy         <= 1'b0;
            bit_count    <= 4'd0;
            tx_shift_reg <= 11'h7FF;
        end else begin
            case (state)
                IDLE: begin
                    serial_out <= 1'b1;
                    busy       <= 1'b0;
                    bit_count  <= 4'd0;
                end
                LOAD: begin
                    busy         <= 1'b1;
                    tx_shift_reg <= {1'b1, parity_bit, tx_data_in, 1'b0}; 
                end
                SHIFT: begin
                    busy         <= 1'b1;
                    serial_out   <= tx_shift_reg[0];
                    tx_shift_reg <= {1'b1, tx_shift_reg[10:1]};
                    bit_count    <= bit_count + 1'b1;
                end
                WAIT: begin
                    busy      <= 1'b0;
                    bit_count <= 4'd0;
                end
            endcase
        end
    end
endmodule

tb_uart_system.v
`timescale 1ns/1ps
`include "uart_transmitter.v"
`include "uart_receiver.v"

module tb_uart_system;
    reg sys_clk;
    reg rst_n;
    reg tx_enable;
    reg [7:0] tx_data_in;
    reg even_odd;

    wire serial_line;
    wire tx_busy;
    wire rx_busy;
    wire rx_data_valid;
    wire [7:0] rx_parallel_out;

    uart_transmitter tx_inst (
        .sys_clk(sys_clk),
        .rst_n(rst_n),
        .tx_enable(tx_enable),
        .tx_data_in(tx_data_in),
        .even_odd(even_odd),
        .serial_out(serial_line),
        .busy(tx_busy)
    );

    uart_receiver rx_inst (
        .sys_clk(sys_clk),
        .rst_n(rst_n),
        .serial_data_in(serial_line),
        .parallel_data_out(rx_parallel_out),
        .data_valid(rx_data_valid),
        .busy(rx_busy)
    );

    // 64 MHz Clock Generator
    always #7.8125 sys_clk = ~sys_clk;

    initial begin
        $dumpfile("uart_simulation.vcd");
        $dumpvars(0, tb_uart_system);

        sys_clk    = 0;
        rst_n      = 0;
        tx_enable  = 0;
        tx_data_in = 8'b0;
        even_odd   = 1'b1; // Odd parity configuration

        #50;
        rst_n = 1; 
        #50;

        // Packet 1: 8'hAA
        tx_data_in = 8'hAA;
        tx_enable  = 1;
        #300;
        tx_enable  = 0;

        @(posedge rx_data_valid);
        $display("[TIME: %t] Captured: 0x%h (Expected: 0xAA)", $time, rx_parallel_out);
        
        #5000;
        
        // Packet 2: 8'hCC
        tx_data_in = 8'hCC;
        tx_enable  = 1;
        #300;
        tx_enable  = 0;

        @(posedge rx_data_valid);
        $display("[TIME: %t] Captured: 0x%h (Expected: 0xCC)", $time, rx_parallel_out);

        #10000;
        $finish;
    end
endmodule

uart_simulation.vcd
$date
	Fri Jul 03 13:03:22 2026
$end
$version
	Icarus Verilog
$end
$timescale
	1ps
$end
$scope module tb_uart_system $end
$var wire 1 ! tx_busy $end
$var wire 1 " serial_line $end
$var wire 8 # rx_parallel_out [7:0] $end
$var wire 1 $ rx_data_valid $end
$var wire 1 % rx_busy $end
$var reg 1 & even_odd $end
$var reg 1 ' rst_n $end
$var reg 1 ( sys_clk $end
$var reg 8 ) tx_data_in [7:0] $end
$var reg 1 * tx_enable $end
$scope module rx_inst $end
$var wire 1 ' rst_n $end
$var wire 1 ( sys_clk $end
$var wire 1 + start_detect_pulse $end
$var wire 1 " serial_data_in $end
$var wire 1 , baud_clk $end
$var reg 4 - bit_count [3:0] $end
$var reg 1 % busy $end
$var reg 1 $ data_valid $end
$var reg 2 . next_state [1:0] $end
$var reg 8 / parallel_data_out [7:0] $end
$var reg 11 0 rx_shift_reg [10:0] $end
$var reg 1 1 start_flag $end
$var reg 2 2 state [1:0] $end
$scope module b_gen $end
$var wire 1 ' rst_n $end
$var wire 1 ( sys_clk $end
$var reg 1 , baud_clk $end
$var reg 4 3 counter [3:0] $end
$upscope $end
$scope module ed_det $end
$var wire 1 + neg_edge $end
$var wire 1 ' rst_n $end
$var wire 1 ( sys_clk $end
$var wire 1 " signal_in $end
$var reg 1 4 delay_reg $end
$upscope $end
$upscope $end
$scope module tx_inst $end
$var wire 1 & even_odd $end
$var wire 1 ' rst_n $end
$var wire 1 ( sys_clk $end
$var wire 8 5 tx_data_in [7:0] $end
$var wire 1 * tx_enable $end
$var wire 1 6 parity_bit $end
$var wire 1 7 baud_clk $end
$var reg 4 8 bit_count [3:0] $end
$var reg 1 ! busy $end
$var reg 2 9 next_state [1:0] $end
$var reg 1 " serial_out $end
$var reg 2 : state [1:0] $end
$var reg 11 ; tx_shift_reg [10:0] $end
$scope module b_gen $end
$var wire 1 ' rst_n $end
$var wire 1 ( sys_clk $end
$var reg 1 7 baud_clk $end
$var reg 4 < counter [3:0] $end
$upscope $end
$scope module p_gen $end
$var wire 1 & even_odd $end
$var wire 8 = tx_data_in [7:0] $end
$var reg 1 6 parity_bit $end
$upscope $end
$upscope $end
$upscope $end
$enddefinitions $end
#0
$dumpvars
b0 =
b0 <
b11111111111 ;
b0 :
b0 9
b0 8
07
16
b0 5
14
b0 3
b0 2
01
b0 0
b0 /
b0 .
b0 -
0,
0+
0*
b0 )
0(
0'
1&
0%
0$
b0 #
1"
0!
$end
#7813
1(
#15626
0(
#23439
1(
#31252
0(
#39065
1(
#46878
0(
#50000
1'
#54691
b1 <
b1 3
1(
#62504
0(
#70317
b10 3
b10 <
1(
#78130
0(
#85943
b11 <
b11 3
1(
#93756
0(
#100000
b1 9
1*
b10101010 )
b10101010 5
b10101010 =
#101569
b100 3
b100 <
1(
#109382
0(
#117195
b101 <
b101 3
1(
#125008
0(
#132821
b110 3
b110 <
1(
#140634
0(
#148447
b111 <
b111 3
1(
#156260
0(
#164073
b10 9
b1 :
1,
b0 3
17
b0 <
1(
#171886
0(
#179699
b1 <
b1 3
1(
#187512
0(
#195325
b10 3
b10 <
1(
#203138
0(
#210951
b11 <
b11 3
1(
#218764
0(
#226577
b100 3
b100 <
1(
#234390
0(
#242203
b101 <
b101 3
1(
#250016
0(
#257829
b110 3
b110 <
1(
#265642
0(
#273455
b111 <
b111 3
1(
#281268
0(
#289081
0,
b0 3
07
b0 <
1(
#296894
0(
#304707
b1 <
b1 3
1(
#312520
0(
#320333
b10 3
b10 <
1(
#328146
0(
#335959
b11 <
b11 3
1(
#343772
0(
#351585
b100 3
b100 <
1(
#359398
0(
#367211
b101 <
b101 3
1(
#375024
0(
#382837
b110 3
b110 <
1(
#390650
0(
#398463
b111 <
b111 3
1(
#400000
0*
#406276
0(
#414089
b10 :
b11101010100 ;
1!
1,
b0 3
17
b0 <
1(
#421902
0(
#429715
b1 <
b1 3
1(
#437528
0(
#445341
b10 3
b10 <
1(
#453154
0(
#460967
b11 <
b11 3
1(
#468780
0(
#476593
b100 3
b100 <
1(
#484406
0(
#492219
b101 <
b101 3
1(
#500032
0(
#507845
b110 3
b110 <
1(
#515658
0(
#523471
b111 <
b111 3
1(
#531284
0(
#539097
0,
b0 3
07
b0 <
1(
#546910
0(
#554723
b1 <
b1 3
1(
#562536
0(
#570349
b10 3
b10 <
1(
#578162
0(
#585975
b11 <
b11 3
1(
#593788
0(
#601601
b100 3
b100 <
1(
#609414
0(
#617227
b101 <
b101 3
1(
#625040
0(
#632853
b110 3
b110 <
1(
#640666
0(
#648479
b111 <
b111 3
1(
#656292
0(
#664105
1+
b1 8
b11110101010 ;
0"
1,
b0 3
17
b0 <
1(
#671918
b1 .
11
0(
#679731
0+
b1 <
b1 3
04
1(
#687544
0(
#695357
b10 3
b10 <
1(
#703170
0(
#710983
b11 <
b11 3
1(
#718796
0(
#726609
b100 3
b100 <
1(
#734422
0(
#742235
b101 <
b101 3
1(
#750048
0(
#757861
b110 3
b110 <
1(
#765674
0(
#773487
b111 <
b111 3
1(
#781300
0(
#789113
0,
b0 3
07
b0 <
1(
#796926
0(
#804739
b1 <
b1 3
1(
#812552
0(
#820365
b10 3
b10 <
1(
#828178
0(
#835991
b11 <
b11 3
1(
#843804
0(
#851617
b100 3
b100 <
1(
#859430
0(
#867243
b101 <
b101 3
1(
#875056
0(
#882869
b110 3
b110 <
1(
#890682
0(
#898495
b111 <
b111 3
1(
#906308
0(
#914121
b1 2
b10 8
b11111010101 ;
1,
b0 3
17
b0 <
1(
#921934
01
0(
#929747
b1 <
b1 3
1(
#937560
0(
#945373
b10 3
b10 <
1(
#953186
0(
#960999
b11 <
b11 3
1(
#968812
0(
#976625
b100 3
b100 <
1(
#984438
0(
#992251
b101 <
b101 3
1(
#1000064
0(
#1007877
b110 3
b110 <
1(
#1015690
0(
#1023503
b111 <
b111 3
1(
#1031316
0(
#1039129
b1 -
1%
0,
b0 3
07
b0 <
1(
#1046942
0(
#1054755
b1 <
b1 3
1(
#1062568
0(
#1070381
b10 3
b10 <
1(
#1078194
0(
#1086007
b11 <
b11 3
1(
#1093820
0(
#1101633
b100 3
b100 <
1(
#1109446
0(
#1117259
b101 <
b101 3
1(
#1125072
0(
#1132885
b110 3
b110 <
1(
#1140698
0(
#1148511
b111 <
b111 3
1(
#1156324
0(
#1164137
b11 8
b11111101010 ;
1"
1,
b0 3
17
b0 <
1(
#1171950
0(
#1179763
b1 <
b1 3
14
1(
#1187576
0(
#1195389
b10 3
b10 <
1(
#1203202
0(
#1211015
b11 <
b11 3
1(
#1218828
0(
#1226641
b100 3
b100 <
1(
#1234454
0(
#1242267
b101 <
b101 3
1(
#1250080
0(
#1257893
b110 3
b110 <
1(
#1265706
0(
#1273519
b111 <
b111 3
1(
#1281332
0(
#1289145
b10 -
b10000000000 0
0,
b0 3
07
b0 <
1(
#1296958
0(
#1304771
b1 <
b1 3
1(
#1312584
0(
#1320397
b10 3
b10 <
1(
#1328210
0(
#1336023
b11 <
b11 3
1(
#1343836
0(
#1351649
b100 3
b100 <
1(
#1359462
0(
#1367275
b101 <
b101 3
1(
#1375088
0(
#1382901
b110 3
b110 <
1(
#1390714
0(
#1398527
b111 <
b111 3
1(
#1406340
0(
#1414153
1+
b100 8
b11111110101 ;
0"
1,
b0 3
17
b0 <
1(
#1421966
11
0(
#1429779
0+
b1 <
b1 3
04
1(
#1437592
01
0(
#1445405
b10 3
b10 <
1(
#1453218
0(
#1461031
b11 <
b11 3
1(
#1468844
0(
#1476657
b100 3
b100 <
1(
#1484470
0(
#1492283
b101 <
b101 3
1(
#1500096
0(
#1507909
b110 3
b110 <
1(
#1515722
0(
#1523535
b111 <
b111 3
1(
#1531348
0(
#1539161
b11 -
b1000000000 0
0,
b0 3
07
b0 <
1(
#1546974
0(
#1554787
b1 <
b1 3
1(
#1562600
0(
#1570413
b10 3
b10 <
1(
#1578226
0(
#1586039
b11 <
b11 3
1(
#1593852
0(
#1601665
b100 3
b100 <
1(
#1609478
0(
#1617291
b101 <
b101 3
1(
#1625104
0(
#1632917
b110 3
b110 <
1(
#1640730
0(
#1648543
b111 <
b111 3
1(
#1656356
0(
#1664169
b101 8
b11111111010 ;
1"
1,
b0 3
17
b0 <
1(
#1671982
0(
#1679795
b1 <
b1 3
14
1(
#1687608
0(
#1695421
b10 3
b10 <
1(
#1703234
0(
#1711047
b11 <
b11 3
1(
#1718860
0(
#1726673
b100 3
b100 <
1(
#1734486
0(
#1742299
b101 <
b101 3
1(
#1750112
0(
#1757925
b110 3
b110 <
1(
#1765738
0(
#1773551
b111 <
b111 3
1(
#1781364
0(
#1789177
b100 -
b10100000000 0
0,
b0 3
07
b0 <
1(
#1796990
0(
#1804803
b1 <
b1 3
1(
#1812616
0(
#1820429
b10 3
b10 <
1(
#1828242
0(
#1836055
b11 <
b11 3
1(
#1843868
0(
#1851681
b100 3
b100 <
1(
#1859494
0(
#1867307
b101 <
b101 3
1(
#1875120
0(
#1882933
b110 3
b110 <
1(
#1890746
0(
#1898559
b111 <
b111 3
1(
#1906372
0(
#1914185
1+
b110 8
b11111111101 ;
0"
1,
b0 3
17
b0 <
1(
#1921998
11
0(
#1929811
0+
b1 <
b1 3
04
1(
#1937624
01
0(
#1945437
b10 3
b10 <
1(
#1953250
0(
#1961063
b11 <
b11 3
1(
#1968876
0(
#1976689
b100 3
b100 <
1(
#1984502
0(
#1992315
b101 <
b101 3
1(
#2000128
0(
#2007941
b110 3
b110 <
1(
#2015754
0(
#2023567
b111 <
b111 3
1(
#2031380
0(
#2039193
b101 -
b1010000000 0
0,
b0 3
07
b0 <
1(
#2047006
0(
#2054819
b1 <
b1 3
1(
#2062632
0(
#2070445
b10 3
b10 <
1(
#2078258
0(
#2086071
b11 <
b11 3
1(
#2093884
0(
#2101697
b100 3
b100 <
1(
#2109510
0(
#2117323
b101 <
b101 3
1(
#2125136
0(
#2132949
b110 3
b110 <
1(
#2140762
0(
#2148575
b111 <
b111 3
1(
#2156388
0(
#2164201
b111 8
b11111111110 ;
1"
1,
b0 3
17
b0 <
1(
#2172014
0(
#2179827
b1 <
b1 3
14
1(
#2187640
0(
#2195453
b10 3
b10 <
1(
#2203266
0(
#2211079
b11 <
b11 3
1(
#2218892
0(
#2226705
b100 3
b100 <
1(
#2234518
0(
#2242331
b101 <
b101 3
1(
#2250144
0(
#2257957
b110 3
b110 <
1(
#2265770
0(
#2273583
b111 <
b111 3
1(
#2281396
0(
#2289209
b110 -
b10101000000 0
0,
b0 3
07
b0 <
1(
#2297022
0(
#2304835
b1 <
b1 3
1(
#2312648
0(
#2320461
b10 3
b10 <
1(
#2328274
0(
#2336087
b11 <
b11 3
1(
#2343900
0(
#2351713
b100 3
b100 <
1(
#2359526
0(
#2367339
b101 <
b101 3
1(
#2375152
0(
#2382965
b110 3
b110 <
1(
#2390778
0(
#2398591
b111 <
b111 3
1(
#2406404
0(
#2414217
1+
b1000 8
b11111111111 ;
0"
1,
b0 3
17
b0 <
1(
#2422030
11
0(
#2429843
0+
b1 <
b1 3
04
1(
#2437656
01
0(
#2445469
b10 3
b10 <
1(
#2453282
0(
#2461095
b11 <
b11 3
1(
#2468908
0(
#2476721
b100 3
b100 <
1(
#2484534
0(
#2492347
b101 <
b101 3
1(
#2500160
0(
#2507973
b110 3
b110 <
1(
#2515786
0(
#2523599
b111 <
b111 3
1(
#2531412
0(
#2539225
b111 -
b1010100000 0
0,
b0 3
07
b0 <
1(
#2547038
0(
#2554851
b1 <
b1 3
1(
#2562664
0(
#2570477
b10 3
b10 <
1(
#2578290
0(
#2586103
b11 <
b11 3
1(
#2593916
0(
#2601729
b100 3
b100 <
1(
#2609542
0(
#2617355
b101 <
b101 3
1(
#2625168
0(
#2632981
b110 3
b110 <
1(
#2640794
0(
#2648607
b111 <
b111 3
1(
#2656420
0(
#2664233
b1001 8
1"
1,
b0 3
17
b0 <
1(
#2672046
0(
#2679859
b1 <
b1 3
14
1(
#2687672
0(
#2695485
b10 3
b10 <
1(
#2703298
0(
#2711111
b11 <
b11 3
1(
#2718924
0(
#2726737
b100 3
b100 <
1(
#2734550
0(
#2742363
b101 <
b101 3
1(
#2750176
0(
#2757989
b110 3
b110 <
1(
#2765802
0(
#2773615
b111 <
b111 3
1(
#2781428
0(
#2789241
b1000 -
b10101010000 0
0,
b0 3
07
b0 <
1(
#2797054
0(
#2804867
b1 <
b1 3
1(
#2812680
0(
#2820493
b10 3
b10 <
1(
#2828306
0(
#2836119
b11 <
b11 3
1(
#2843932
0(
#2851745
b100 3
b100 <
1(
#2859558
0(
#2867371
b101 <
b101 3
1(
#2875184
0(
#2882997
b110 3
b110 <
1(
#2890810
0(
#2898623
b111 <
b111 3
1(
#2906436
0(
#2914249
b1010 8
1,
b0 3
17
b0 <
1(
#2922062
0(
#2929875
b1 <
b1 3
1(
#2937688
0(
#2945501
b10 3
b10 <
1(
#2953314
0(
#2961127
b11 <
b11 3
1(
#2968940
0(
#2976753
b100 3
b100 <
1(
#2984566
0(
#2992379
b101 <
b101 3
1(
#3000192
0(
#3008005
b110 3
b110 <
1(
#3015818
0(
#3023631
b111 <
b111 3
1(
#3031444
0(
#3039257
b1001 -
b11010101000 0
0,
b0 3
07
b0 <
1(
#3047070
0(
#3054883
b1 <
b1 3
1(
#3062696
0(
#3070509
b10 3
b10 <
1(
#3078322
0(
#3086135
b11 <
b11 3
1(
#3093948
0(
#3101761
b100 3
b100 <
1(
#3109574
0(
#3117387
b101 <
b101 3
1(
#3125200
0(
#3133013
b110 3
b110 <
1(
#3140826
0(
#3148639
b111 <
b111 3
1(
#3156452
0(
#3164265
b11 9
b1011 8
1,
b0 3
17
b0 <
1(
#3172078
0(
#3179891
b1 <
b1 3
1(
#3187704
0(
#3195517
b10 3
b10 <
1(
#3203330
0(
#3211143
b11 <
b11 3
1(
#3218956
0(
#3226769
b100 3
b100 <
1(
#3234582
0(
#3242395
b101 <
b101 3
1(
#3250208
0(
#3258021
b110 3
b110 <
1(
#3265834
0(
#3273647
b111 <
b111 3
1(
#3281460
0(
#3289273
b10 .
b1010 -
b11101010100 0
0,
b0 3
07
b0 <
1(
#3297086
0(
#3304899
b1 <
b1 3
1(
#3312712
0(
#3320525
b10 3
b10 <
1(
#3328338
0(
#3336151
b11 <
b11 3
1(
#3343964
0(
#3351777
b100 3
b100 <
1(
#3359590
0(
#3367403
b101 <
b101 3
1(
#3375216
0(
#3383029
b110 3
b110 <
1(
#3390842
0(
#3398655
b111 <
b111 3
1(
#3406468
0(
#3414281
b11 .
b0 9
b10 2
b11 :
b1100 8
1,
b0 3
17
b0 <
1(
#3422094
0(
#3429907
b1 <
b1 3
1(
#3437720
0(
#3445533
b10 3
b10 <
1(
#3453346
0(
#3461159
b11 <
b11 3
1(
#3468972
0(
#3476785
b100 3
b100 <
1(
#3484598
0(
#3492411
b101 <
b101 3
1(
#3500224
0(
#3508037
b110 3
b110 <
1(
#3515850
0(
#3523663
b111 <
b111 3
1(
#3531476
0(
#3539289
1$
b10101010 #
b10101010 /
0,
b0 3
07
b0 <
1(
#3547102
0(
#3554915
b1 <
b1 3
1(
#3562728
0(
#3570541
b10 3
b10 <
1(
#3578354
0(
#3586167
b11 <
b11 3
1(
#3593980
0(
#3601793
b100 3
b100 <
1(
#3609606
0(
#3617419
b101 <
b101 3
1(
#3625232
0(
#3633045
b110 3
b110 <
1(
#3640858
0(
#3648671
b111 <
b111 3
1(
#3656484
0(
#3664297
b0 .
b11 2
b0 8
0!
b0 :
1,
b0 3
17
b0 <
1(
#3672110
0(
#3679923
b1 <
b1 3
1(
#3687736
0(
#3695549
b10 3
b10 <
1(
#3703362
0(
#3711175
b11 <
b11 3
1(
#3718988
0(
#3726801
b100 3
b100 <
1(
#3734614
0(
#3742427
b101 <
b101 3
1(
#3750240
0(
#3758053
b110 3
b110 <
1(
#3765866
0(
#3773679
b111 <
b111 3
1(
#3781492
0(
#3789305
0$
0%
0,
b0 3
07
b0 <
1(
#3797118
0(
#3804931
b1 <
b1 3
1(
#3812744
0(
#3820557
b10 3
b10 <
1(
#3828370
0(
#3836183
b11 <
b11 3
1(
#3843996
0(
#3851809
b100 3
b100 <
1(
#3859622
0(
#3867435
b101 <
b101 3
1(
#3875248
0(
#3883061
b110 3
b110 <
1(
#3890874
0(
#3898687
b111 <
b111 3
1(
#3906500
0(
#3914313
b0 2
1,
b0 3
17
b0 <
1(
#3922126
0(
#3929939
b1 <
b1 3
1(
#3937752
0(
#3945565
b10 3
b10 <
1(
#3953378
0(
#3961191
b11 <
b11 3
1(
#3969004
0(
#3976817
b100 3
b100 <
1(
#3984630
0(
#3992443
b101 <
b101 3
1(
#4000256
0(
#4008069
b110 3
b110 <
1(
#4015882
0(
#4023695
b111 <
b111 3
1(
#4031508
0(
#4039321
b0 -
0,
b0 3
07
b0 <
1(
#4047134
0(
#4054947
b1 <
b1 3
1(
#4062760
0(
#4070573
b10 3
b10 <
1(
#4078386
0(
#4086199
b11 <
b11 3
1(
#4094012
0(
#4101825
b100 3
b100 <
1(
#4109638
0(
#4117451
b101 <
b101 3
1(
#4125264
0(
#4133077
b110 3
b110 <
1(
#4140890
0(
#4148703
b111 <
b111 3
1(
#4156516
0(
#4164329
1,
b0 3
17
b0 <
1(
#4172142
0(
#4179955
b1 <
b1 3
1(
#4187768
0(
#4195581
b10 3
b10 <
1(
#4203394
0(
#4211207
b11 <
b11 3
1(
#4219020
0(
#4226833
b100 3
b100 <
1(
#4234646
0(
#4242459
b101 <
b101 3
1(
#4250272
0(
#4258085
b110 3
b110 <
1(
#4265898
0(
#4273711
b111 <
b111 3
1(
#4281524
0(
#4289337
0,
b0 3
07
b0 <
1(
#4297150
0(
#4304963
b1 <
b1 3
1(
#4312776
0(
#4320589
b10 3
b10 <
1(
#4328402
0(
#4336215
b11 <
b11 3
1(
#4344028
0(
#4351841
b100 3
b100 <
1(
#4359654
0(
#4367467
b101 <
b101 3
1(
#4375280
0(
#4383093
b110 3
b110 <
1(
#4390906
0(
#4398719
b111 <
b111 3
1(
#4406532
0(
#4414345
1,
b0 3
17
b0 <
1(
#4422158
0(
#4429971
b1 <
b1 3
1(
#4437784
0(
#4445597
b10 3
b10 <
1(
#4453410
0(
#4461223
b11 <
b11 3
1(
#4469036
0(
#4476849
b100 3
b100 <
1(
#4484662
0(
#4492475
b101 <
b101 3
1(
#4500288
0(
#4508101
b110 3
b110 <
1(
#4515914
0(
#4523727
b111 <
b111 3
1(
#4531540
0(
#4539353
0,
b0 3
07
b0 <
1(
#4547166
0(
#4554979
b1 <
b1 3
1(
#4562792
0(
#4570605
b10 3
b10 <
1(
#4578418
0(
#4586231
b11 <
b11 3
1(
#4594044
0(
#4601857
b100 3
b100 <
1(
#4609670
0(
#4617483
b101 <
b101 3
1(
#4625296
0(
#4633109
b110 3
b110 <
1(
#4640922
0(
#4648735
b111 <
b111 3
1(
#4656548
0(
#4664361
1,
b0 3
17
b0 <
1(
#4672174
0(
#4679987
b1 <
b1 3
1(
#4687800
0(
#4695613
b10 3
b10 <
1(
#4703426
0(
#4711239
b11 <
b11 3
1(
#4719052
0(
#4726865
b100 3
b100 <
1(
#4734678
0(
#4742491
b101 <
b101 3
1(
#4750304
0(
#4758117
b110 3
b110 <
1(
#4765930
0(
#4773743
b111 <
b111 3
1(
#4781556
0(
#4789369
0,
b0 3
07
b0 <
1(
#4797182
0(
#4804995
b1 <
b1 3
1(
#4812808
0(
#4820621
b10 3
b10 <
1(
#4828434
0(
#4836247
b11 <
b11 3
1(
#4844060
0(
#4851873
b100 3
b100 <
1(
#4859686
0(
#4867499
b101 <
b101 3
1(
#4875312
0(
#4883125
b110 3
b110 <
1(
#4890938
0(
#4898751
b111 <
b111 3
1(
#4906564
0(
#4914377
1,
b0 3
17
b0 <
1(
#4922190
0(
#4930003
b1 <
b1 3
1(
#4937816
0(
#4945629
b10 3
b10 <
1(
#4953442
0(
#4961255
b11 <
b11 3
1(
#4969068
0(
#4976881
b100 3
b100 <
1(
#4984694
0(
#4992507
b101 <
b101 3
1(
#5000320
0(
#5008133
b110 3
b110 <
1(
#5015946
0(
#5023759
b111 <
b111 3
1(
#5031572
0(
#5039385
0,
b0 3
07
b0 <
1(
#5047198
0(
#5055011
b1 <
b1 3
1(
#5062824
0(
#5070637
b10 3
b10 <
1(
#5078450
0(
#5086263
b11 <
b11 3
1(
#5094076
0(
#5101889
b100 3
b100 <
1(
#5109702
0(
#5117515
b101 <
b101 3
1(
#5125328
0(
#5133141
b110 3
b110 <
1(
#5140954
0(
#5148767
b111 <
b111 3
1(
#5156580
0(
#5164393
1,
b0 3
17
b0 <
1(
#5172206
0(
#5180019
b1 <
b1 3
1(
#5187832
0(
#5195645
b10 3
b10 <
1(
#5203458
0(
#5211271
b11 <
b11 3
1(
#5219084
0(
#5226897
b100 3
b100 <
1(
#5234710
0(
#5242523
b101 <
b101 3
1(
#5250336
0(
#5258149
b110 3
b110 <
1(
#5265962
0(
#5273775
b111 <
b111 3
1(
#5281588
0(
#5289401
0,
b0 3
07
b0 <
1(
#5297214
0(
#5305027
b1 <
b1 3
1(
#5312840
0(
#5320653
b10 3
b10 <
1(
#5328466
0(
#5336279
b11 <
b11 3
1(
#5344092
0(
#5351905
b100 3
b100 <
1(
#5359718
0(
#5367531
b101 <
b101 3
1(
#5375344
0(
#5383157
b110 3
b110 <
1(
#5390970
0(
#5398783
b111 <
b111 3
1(
#5406596
0(
#5414409
1,
b0 3
17
b0 <
1(
#5422222
0(
#5430035
b1 <
b1 3
1(
#5437848
0(
#5445661
b10 3
b10 <
1(
#5453474
0(
#5461287
b11 <
b11 3
1(
#5469100
0(
#5476913
b100 3
b100 <
1(
#5484726
0(
#5492539
b101 <
b101 3
1(
#5500352
0(
#5508165
b110 3
b110 <
1(
#5515978
0(
#5523791
b111 <
b111 3
1(
#5531604
0(
#5539417
0,
b0 3
07
b0 <
1(
#5547230
0(
#5555043
b1 <
b1 3
1(
#5562856
0(
#5570669
b10 3
b10 <
1(
#5578482
0(
#5586295
b11 <
b11 3
1(
#5594108
0(
#5601921
b100 3
b100 <
1(
#5609734
0(
#5617547
b101 <
b101 3
1(
#5625360
0(
#5633173
b110 3
b110 <
1(
#5640986
0(
